devforge/__init__.py
devforge/cli.py
devforge/__pycache__/__init__.cpython-312.pyc
devforge/__pycache__/cli.cpython-312.pyc
devforge/scaffolders/__init__.py
devforge/scaffolders/base.py
devforge/scaffolders/fastapi.py
devforge/scaffolders/flutter.py
devforge/scaffolders/react.py
devforge/scaffolders/__pycache__/__init__.cpython-312.pyc
devforge/scaffolders/__pycache__/base.cpython-312.pyc
devforge/scaffolders/__pycache__/fastapi.cpython-312.pyc
devforge/scaffolders/__pycache__/flutter.cpython-312.pyc
devforge/scaffolders/__pycache__/react.cpython-312.pyc
devforge_cli-1.0.1.dist-info/licenses/LICENSE
devforge_cli-1.0.1.dist-info/METADATA
devforge_cli-1.0.1.dist-info/WHEEL
devforge_cli-1.0.1.dist-info/entry_points.txt
devforge_cli-1.0.1.dist-info/top_level.txt
devforge_cli-1.0.1.dist-info/RECORD
