Metadata-Version: 2.4
Name: devforge-cli
Version: 1.0.1
Summary: Universal project scaffolder for React, FastAPI, and Flutter
Home-page: https://github.com/isaka-12/devforge
Author: Isaka Mtweve
Author-email: Isaka Mtweve <isakamtweve69@gmail.com>
License: MIT
Project-URL: Homepage, https://github.com/isakamtweve/devforge
Project-URL: Documentation, https://github.com/isakamtweve/devforge#readme
Project-URL: Repository, https://github.com/isakamtweve/devforge
Project-URL: Bug Reports, https://github.com/isakamtweve/devforge/issues
Keywords: scaffolding,code generator,react,fastapi,flutter,cli,boilerplate
Classifier: Development Status :: 4 - Beta
Classifier: Intended Audience :: Developers
Classifier: Topic :: Software Development :: Code Generators
Classifier: License :: OSI Approved :: MIT License
Classifier: Programming Language :: Python :: 3
Classifier: Programming Language :: Python :: 3.8
Classifier: Programming Language :: Python :: 3.9
Classifier: Programming Language :: Python :: 3.10
Classifier: Programming Language :: Python :: 3.11
Classifier: Programming Language :: Python :: 3.12
Classifier: Operating System :: OS Independent
Classifier: Environment :: Console
Requires-Python: >=3.8
License-File: LICENSE
Requires-Dist: click>=8.0.0
Dynamic: author
Dynamic: home-page
Dynamic: license-file
Dynamic: requires-python
